boto_s3_presignedurl/__init__.py
Boto_S3_PresignedUrl-0.0.0.dist-info/LICENSE
Boto_S3_PresignedUrl-0.0.0.dist-info/METADATA
Boto_S3_PresignedUrl-0.0.0.dist-info/WHEEL
Boto_S3_PresignedUrl-0.0.0.dist-info/top_level.txt
Boto_S3_PresignedUrl-0.0.0.dist-info/RECORD
