Metadata-Version: 2.1
Name: Boto-S3-PresignedUrl
Version: 0.0.0
Summary: A personal package
Home-page: https://github.com
Author: spyc
Author-email: unknown@gmail.com
License: MIT
Platform: UNKNOWN
Classifier: Programming Language :: Python :: 3
Classifier: License :: OSI Approved :: MIT License
Classifier: Operating System :: OS Independent
Requires-Dist: boto3
